MANIFEST.in
README.rst
setup.py
docs/HISTORY.rst
docs/INSTALL.txt
docs/LICENSE.GPL
docs/LICENSE.txt
redturtle/__init__.py
redturtle.smartlink.egg-info/PKG-INFO
redturtle.smartlink.egg-info/SOURCES.txt
redturtle.smartlink.egg-info/dependency_links.txt
redturtle.smartlink.egg-info/entry_points.txt
redturtle.smartlink.egg-info/namespace_packages.txt
redturtle.smartlink.egg-info/not-zip-safe
redturtle.smartlink.egg-info/requires.txt
redturtle.smartlink.egg-info/top_level.txt
redturtle/smartlink/README.txt
redturtle/smartlink/__init__.py
redturtle/smartlink/config.py
redturtle/smartlink/configure.zcml
redturtle/smartlink/extender.py
redturtle/smartlink/indexers.py
redturtle/smartlink/migrator.py
redturtle/smartlink/setuphandlers.py
redturtle/smartlink/upgrades.zcml
redturtle/smartlink/utility.py
redturtle/smartlink/Extensions/fix_meta_type.py
redturtle/smartlink/Extensions/install.py
redturtle/smartlink/browser/__init__.py
redturtle/smartlink/browser/configlet.py
redturtle/smartlink/browser/configure.zcml
redturtle/smartlink/browser/controlpanel.pt
redturtle/smartlink/browser/fix-fake-internal-links.pt
redturtle/smartlink/browser/link.png
redturtle/smartlink/browser/link_icon.gif
redturtle/smartlink/browser/link_redirect_view.py
redturtle/smartlink/browser/migrate.py
redturtle/smartlink/browser/smart_link.css
redturtle/smartlink/browser/smartlink_view.pt
redturtle/smartlink/browser/smartlink_view.py
redturtle/smartlink/browser/utilities.py
redturtle/smartlink/content/__init__.py
redturtle/smartlink/content/configure.zcml
redturtle/smartlink/content/link.py
redturtle/smartlink/events/__init__.py
redturtle/smartlink/events/configure.zcml
redturtle/smartlink/events/linker.py
redturtle/smartlink/interfaces/__init__.py
redturtle/smartlink/interfaces/link.py
redturtle/smartlink/interfaces/utility.py
redturtle/smartlink/locales/i18n.sh
redturtle/smartlink/locales/redturtle.smartlink-manual.pot
redturtle/smartlink/locales/redturtle.smartlink.pot
redturtle/smartlink/locales/it/LC_MESSAGES/redturtle.smartlink.mo
redturtle/smartlink/locales/it/LC_MESSAGES/redturtle.smartlink.po
redturtle/smartlink/profiles/atLinkToSmartLink/import_steps.xml
redturtle/smartlink/profiles/atLinkToSmartLink/redturtle.smartlink_linkToSmartLink.txt
redturtle/smartlink/profiles/default/componentregistry.xml
