Metadata-Version: 1.1
Name: redturtle.smartlink
Version: 1.3.2
Summary: An advanced Link content type for Plone, with image field, customizable content icon and internal link feature
Home-page: http://plone.org/products/redturtle.smartlink
Author: RedTurtle Technology
Author-email: sviluppoplone@redturtle.it
License: GPL
Keywords: plone archetype link internal content plonegov
Platform: UNKNOWN
Classifier: Development Status :: 5 - Production/Stable
Classifier: Framework :: Plone
Classifier: Framework :: Plone :: 4.1
Classifier: Framework :: Plone :: 4.2
Classifier: Framework :: Plone :: 4.3
Classifier: Programming Language :: Python
Classifier: License :: OSI Approved :: GNU General Public License (GPL)
